[
  {
    "manager":"NH-Amundi운용",
    "etf_name":"HANARO 바이오코리아액티브",
    "short_code":"498050",
    "fund_code":"KR7498050004",
    "holding_name":"에이비엘바이오",
    "current_weight_pct":11.7187531422,
    "previous_weight_pct":11.9589361884,
    "weight_diff_pct":-0.2401830461,
    "change_state":"감소",
    "asof_date":"2026-06-09",
    "source":"FunETF"
  },
  {
    "manager":"NH-Amundi운용",
    "etf_name":"HANARO 바이오코리아액티브",
    "short_code":"498050",
    "fund_code":"KR7498050004",
    "holding_name":"리가켐바이오",
    "current_weight_pct":8.0094118415,
    "previous_weight_pct":8.4770969221,
    "weight_diff_pct":-0.4676850806,
    "change_state":"감소",
    "asof_date":"2026-06-09",
    "source":"FunETF"
  },
  {
    "manager":"NH-Amundi운용",
    "etf_name":"HANARO 바이오코리아액티브",
    "short_code":"498050",
    "fund_code":"KR7498050004",
    "holding_name":"한올바이오파마",
    "current_weight_pct":6.455131215,
    "previous_weight_pct":6.7184242561,
    "weight_diff_pct":-0.2632930411,
    "change_state":"감소",
    "asof_date":"2026-06-09",
    "source":"FunETF"
  },
  {
    "manager":"타임폴리오",
    "etf_name":"TIME K바이오액티브",
    "short_code":"463050",
    "fund_code":"KR7463050005",
    "holding_name":"셀트리온",
    "current_weight_pct":10.27,
    "previous_weight_pct":9.78,
    "weight_diff_pct":0.49,
    "change_state":"증가",
    "asof_date":"2026-06-09",
    "source":"TIME"
  },
  {
    "manager":"타임폴리오",
    "etf_name":"TIME K바이오액티브",
    "short_code":"463050",
    "fund_code":"KR7463050005",
    "holding_name":"알테오젠",
    "current_weight_pct":9.77,
    "previous_weight_pct":9.93,
    "weight_diff_pct":-0.16,
    "change_state":"감소",
    "asof_date":"2026-06-09",
    "source":"TIME"
  },
  {
    "manager":"타임폴리오",
    "etf_name":"TIME K바이오액티브",
    "short_code":"463050",
    "fund_code":"KR7463050005",
    "holding_name":"삼성바이오로직스",
    "current_weight_pct":7.63,
    "previous_weight_pct":7.28,
    "weight_diff_pct":0.35,
    "change_state":"증가",
    "asof_date":"2026-06-09",
    "source":"TIME"
  },
  {
    "manager":"타임폴리오",
    "etf_name":"TIME K바이오액티브",
    "short_code":"463050",
    "fund_code":"KR7463050005",
    "holding_name":"한미약품",
    "current_weight_pct":7.6,
    "previous_weight_pct":8.05,
    "weight_diff_pct":-0.45,
    "change_state":"감소",
    "asof_date":"2026-06-09",
    "source":"TIME"
  },
  {
    "manager":"타임폴리오",
    "etf_name":"TIME K바이오액티브",
    "short_code":"463050",
    "fund_code":"KR7463050005",
    "holding_name":"올릭스",
    "current_weight_pct":6.53,
    "previous_weight_pct":7.03,
    "weight_diff_pct":-0.5,
    "change_state":"감소",
    "asof_date":"2026-06-09",
    "source":"TIME"
  },
  {
    "manager":"타임폴리오",
    "etf_name":"TIME K바이오액티브",
    "short_code":"463050",
    "fund_code":"KR7463050005",
    "holding_name":"리가켐바이오",
    "current_weight_pct":5.36,
    "previous_weight_pct":5.54,
    "weight_diff_pct":-0.18,
    "change_state":"감소",
    "asof_date":"2026-06-09",
    "source":"TIME"
  },
  {
    "manager":"타임폴리오",
    "etf_name":"TIME K바이오액티브",
    "short_code":"463050",
    "fund_code":"KR7463050005",
    "holding_name":"에스티팜",
    "current_weight_pct":4.2,
    "previous_weight_pct":4.06,
    "weight_diff_pct":0.14,
    "change_state":"증가",
    "asof_date":"2026-06-09",
    "source":"TIME"
  },
  {
    "manager":"타임폴리오",
    "etf_name":"TIME K바이오액티브",
    "short_code":"463050",
    "fund_code":"KR7463050005",
    "holding_name":"디앤디파마텍",
    "current_weight_pct":3.62,
    "previous_weight_pct":3.76,
    "weight_diff_pct":-0.14,
    "change_state":"감소",
    "asof_date":"2026-06-09",
    "source":"TIME"
  },
  {
    "manager":"타임폴리오",
    "etf_name":"TIME K바이오액티브",
    "short_code":"463050",
    "fund_code":"KR7463050005",
    "holding_name":"에이비엘바이오",
    "current_weight_pct":3.4,
    "previous_weight_pct":3.39,
    "weight_diff_pct":0.01,
    "change_state":"증가",
    "asof_date":"2026-06-09",
    "source":"TIME"
  },
  {
    "manager":"타임폴리오",
    "etf_name":"TIME K바이오액티브",
    "short_code":"463050",
    "fund_code":"KR7463050005",
    "holding_name":"에이프릴바이오",
    "current_weight_pct":2.99,
    "previous_weight_pct":3.25,
    "weight_diff_pct":-0.26,
    "change_state":"감소",
    "asof_date":"2026-06-09",
    "source":"TIME"
  },
  {
    "manager":"타임폴리오",
    "etf_name":"TIME K바이오액티브",
    "short_code":"463050",
    "fund_code":"KR7463050005",
    "holding_name":"삼성에피스홀딩스",
    "current_weight_pct":2.49,
    "previous_weight_pct":2.41,
    "weight_diff_pct":0.08,
    "change_state":"증가",
    "asof_date":"2026-06-09",
    "source":"TIME"
  },
  {
    "manager":"타임폴리오",
    "etf_name":"TIME K바이오액티브",
    "short_code":"463050",
    "fund_code":"KR7463050005",
    "holding_name":"셀트리온제약",
    "current_weight_pct":2.49,
    "previous_weight_pct":2.38,
    "weight_diff_pct":0.11,
    "change_state":"증가",
    "asof_date":"2026-06-09",
    "source":"TIME"
  },
  {
    "manager":"타임폴리오",
    "etf_name":"TIME K바이오액티브",
    "short_code":"463050",
    "fund_code":"KR7463050005",
    "holding_name":"알지노믹스",
    "current_weight_pct":2.29,
    "previous_weight_pct":2.43,
    "weight_diff_pct":-0.14,
    "change_state":"감소",
    "asof_date":"2026-06-09",
    "source":"TIME"
  },
  {
    "manager":"타임폴리오",
    "etf_name":"TIME K바이오액티브",
    "short_code":"463050",
    "fund_code":"KR7463050005",
    "holding_name":"HLB",
    "current_weight_pct":2.22,
    "previous_weight_pct":2.06,
    "weight_diff_pct":0.16,
    "change_state":"증가",
    "asof_date":"2026-06-09",
    "source":"TIME"
  },
  {
    "manager":"타임폴리오",
    "etf_name":"TIME K바이오액티브",
    "short_code":"463050",
    "fund_code":"KR7463050005",
    "holding_name":"유한양행",
    "current_weight_pct":2.22,
    "previous_weight_pct":2.11,
    "weight_diff_pct":0.11,
    "change_state":"증가",
    "asof_date":"2026-06-09",
    "source":"TIME"
  },
  {
    "manager":"타임폴리오",
    "etf_name":"TIME K바이오액티브",
    "short_code":"463050",
    "fund_code":"KR7463050005",
    "holding_name":"지투지바이오",
    "current_weight_pct":2.06,
    "previous_weight_pct":2.16,
    "weight_diff_pct":-0.1,
    "change_state":"감소",
    "asof_date":"2026-06-09",
    "source":"TIME"
  },
  {
    "manager":"타임폴리오",
    "etf_name":"TIME K바이오액티브",
    "short_code":"463050",
    "fund_code":"KR7463050005",
    "holding_name":"오스코텍",
    "current_weight_pct":1.87,
    "previous_weight_pct":1.71,
    "weight_diff_pct":0.16,
    "change_state":"증가",
    "asof_date":"2026-06-09",
    "source":"TIME"
  },
  {
    "manager":"타임폴리오",
    "etf_name":"TIME K바이오액티브",
    "short_code":"463050",
    "fund_code":"KR7463050005",
    "holding_name":"펩트론",
    "current_weight_pct":1.77,
    "previous_weight_pct":1.72,
    "weight_diff_pct":0.05,
    "change_state":"증가",
    "asof_date":"2026-06-09",
    "source":"TIME"
  },
  {
    "manager":"타임폴리오",
    "etf_name":"TIME K바이오액티브",
    "short_code":"463050",
    "fund_code":"KR7463050005",
    "holding_name":"인벤티지랩",
    "current_weight_pct":1.75,
    "previous_weight_pct":1.76,
    "weight_diff_pct":-0.01,
    "change_state":"감소",
    "asof_date":"2026-06-09",
    "source":"TIME"
  },
  {
    "manager":"타임폴리오",
    "etf_name":"TIME K바이오액티브",
    "short_code":"463050",
    "fund_code":"KR7463050005",
    "holding_name":"휴젤",
    "current_weight_pct":1.75,
    "previous_weight_pct":1.67,
    "weight_diff_pct":0.08,
    "change_state":"증가",
    "asof_date":"2026-06-09",
    "source":"TIME"
  },
  {
    "manager":"타임폴리오",
    "etf_name":"TIME K바이오액티브",
    "short_code":"463050",
    "fund_code":"KR7463050005",
    "holding_name":"씨어스",
    "current_weight_pct":1.71,
    "previous_weight_pct":1.59,
    "weight_diff_pct":0.12,
    "change_state":"증가",
    "asof_date":"2026-06-09",
    "source":"TIME"
  },
  {
    "manager":"타임폴리오",
    "etf_name":"TIME K바이오액티브",
    "short_code":"463050",
    "fund_code":"KR7463050005",
    "holding_name":"오름테라퓨틱",
    "current_weight_pct":1.68,
    "previous_weight_pct":1.71,
    "weight_diff_pct":-0.03,
    "change_state":"감소",
    "asof_date":"2026-06-09",
    "source":"TIME"
  },
  {
    "manager":"타임폴리오",
    "etf_name":"TIME K바이오액티브",
    "short_code":"463050",
    "fund_code":"KR7463050005",
    "holding_name":"보로노이",
    "current_weight_pct":1.67,
    "previous_weight_pct":1.71,
    "weight_diff_pct":-0.04,
    "change_state":"감소",
    "asof_date":"2026-06-09",
    "source":"TIME"
  },
  {
    "manager":"타임폴리오",
    "etf_name":"TIME K바이오액티브",
    "short_code":"463050",
    "fund_code":"KR7463050005",
    "holding_name":"한올바이오파마",
    "current_weight_pct":1.55,
    "previous_weight_pct":1.57,
    "weight_diff_pct":-0.02,
    "change_state":"감소",
    "asof_date":"2026-06-09",
    "source":"TIME"
  },
  {
    "manager":"타임폴리오",
    "etf_name":"TIME K바이오액티브",
    "short_code":"463050",
    "fund_code":"KR7463050005",
    "holding_name":"현금",
    "current_weight_pct":1.33,
    "previous_weight_pct":1.17,
    "weight_diff_pct":0.16,
    "change_state":"증가",
    "asof_date":"2026-06-09",
    "source":"TIME"
  },
  {
    "manager":"타임폴리오",
    "etf_name":"TIME K바이오액티브",
    "short_code":"463050",
    "fund_code":"KR7463050005",
    "holding_name":"리브스메드",
    "current_weight_pct":1.2,
    "previous_weight_pct":1.25,
    "weight_diff_pct":-0.05,
    "change_state":"감소",
    "asof_date":"2026-06-09",
    "source":"TIME"
  },
  {
    "manager":"타임폴리오",
    "etf_name":"TIME K바이오액티브",
    "short_code":"463050",
    "fund_code":"KR7463050005",
    "holding_name":"파마리서치",
    "current_weight_pct":1.19,
    "previous_weight_pct":1.17,
    "weight_diff_pct":0.02,
    "change_state":"증가",
    "asof_date":"2026-06-09",
    "source":"TIME"
  },
  {
    "manager":"타임폴리오",
    "etf_name":"TIME K바이오액티브",
    "short_code":"463050",
    "fund_code":"KR7463050005",
    "holding_name":"일동제약",
    "current_weight_pct":1.09,
    "previous_weight_pct":1.07,
    "weight_diff_pct":0.02,
    "change_state":"증가",
    "asof_date":"2026-06-09",
    "source":"TIME"
  },
  {
    "manager":"타임폴리오",
    "etf_name":"TIME K바이오액티브",
    "short_code":"463050",
    "fund_code":"KR7463050005",
    "holding_name":"케어젠",
    "current_weight_pct":1.07,
    "previous_weight_pct":1.08,
    "weight_diff_pct":-0.01,
    "change_state":"감소",
    "asof_date":"2026-06-09",
    "source":"TIME"
  },
  {
    "manager":"타임폴리오",
    "etf_name":"TIME K바이오액티브",
    "short_code":"463050",
    "fund_code":"KR7463050005",
    "holding_name":"네이처셀",
    "current_weight_pct":0.9,
    "previous_weight_pct":0.92,
    "weight_diff_pct":-0.02,
    "change_state":"감소",
    "asof_date":"2026-06-09",
    "source":"TIME"
  },
  {
    "manager":"타임폴리오",
    "etf_name":"TIME K바이오액티브",
    "short_code":"463050",
    "fund_code":"KR7463050005",
    "holding_name":"고영",
    "current_weight_pct":0.83,
    "previous_weight_pct":0.83,
    "weight_diff_pct":0.0,
    "change_state":"유지",
    "asof_date":"2026-06-09",
    "source":"TIME"
  },
  {
    "manager":"타임폴리오",
    "etf_name":"TIME K바이오액티브",
    "short_code":"463050",
    "fund_code":"KR7463050005",
    "holding_name":"에임드바이오",
    "current_weight_pct":0.73,
    "previous_weight_pct":0.73,
    "weight_diff_pct":0.0,
    "change_state":"유지",
    "asof_date":"2026-06-09",
    "source":"TIME"
  },
  {
    "manager":"타임폴리오",
    "etf_name":"TIME K바이오액티브",
    "short_code":"463050",
    "fund_code":"KR7463050005",
    "holding_name":"앱클론",
    "current_weight_pct":0.66,
    "previous_weight_pct":0.68,
    "weight_diff_pct":-0.02,
    "change_state":"감소",
    "asof_date":"2026-06-09",
    "source":"TIME"
  },
  {
    "manager":"타임폴리오",
    "etf_name":"TIME K바이오액티브",
    "short_code":"463050",
    "fund_code":"KR7463050005",
    "holding_name":"메쥬",
    "current_weight_pct":0.62,
    "previous_weight_pct":0.62,
    "weight_diff_pct":0.0,
    "change_state":"유지",
    "asof_date":"2026-06-09",
    "source":"TIME"
  },
  {
    "manager":"타임폴리오",
    "etf_name":"TIME K바이오액티브",
    "short_code":"463050",
    "fund_code":"KR7463050005",
    "holding_name":"HK이노엔",
    "current_weight_pct":0.61,
    "previous_weight_pct":0.57,
    "weight_diff_pct":0.04,
    "change_state":"증가",
    "asof_date":"2026-06-09",
    "source":"TIME"
  },
  {
    "manager":"타임폴리오",
    "etf_name":"TIME K바이오액티브",
    "short_code":"463050",
    "fund_code":"KR7463050005",
    "holding_name":"토모큐브",
    "current_weight_pct":0.56,
    "previous_weight_pct":0.55,
    "weight_diff_pct":0.01,
    "change_state":"증가",
    "asof_date":"2026-06-09",
    "source":"TIME"
  },
  {
    "manager":"타임폴리오",
    "etf_name":"TIME K바이오액티브",
    "short_code":"463050",
    "fund_code":"KR7463050005",
    "holding_name":"지아이이노베이션",
    "current_weight_pct":0.33,
    "previous_weight_pct":0.33,
    "weight_diff_pct":0.0,
    "change_state":"유지",
    "asof_date":"2026-06-09",
    "source":"TIME"
  },
  {
    "manager":"미래에셋",
    "etf_name":"TIGER 기술이전바이오액티브",
    "short_code":"0168K0",
    "fund_code":"KR70168K0003",
    "holding_name":"올릭스",
    "current_weight_pct":13.0072753247,
    "previous_weight_pct":13.8681192293,
    "weight_diff_pct":-0.8608439045,
    "change_state":"감소",
    "asof_date":"2026-06-09",
    "source":"FunETF"
  },
  {
    "manager":"미래에셋",
    "etf_name":"TIGER 기술이전바이오액티브",
    "short_code":"0168K0",
    "fund_code":"KR70168K0003",
    "holding_name":"리가켐바이오",
    "current_weight_pct":10.3169088734,
    "previous_weight_pct":10.5704022575,
    "weight_diff_pct":-0.2534933841,
    "change_state":"감소",
    "asof_date":"2026-06-09",
    "source":"FunETF"
  },
  {
    "manager":"미래에셋",
    "etf_name":"TIGER 기술이전바이오액티브",
    "short_code":"0168K0",
    "fund_code":"KR70168K0003",
    "holding_name":"에이비엘바이오",
    "current_weight_pct":6.6692395473,
    "previous_weight_pct":6.588443964,
    "weight_diff_pct":0.0807955832,
    "change_state":"증가",
    "asof_date":"2026-06-09",
    "source":"FunETF"
  },
  {
    "manager":"삼성",
    "etf_name":"KoAct 바이오헬스케어액티브",
    "short_code":"462900",
    "fund_code":"KR7462900002",
    "holding_name":"알테오젠",
    "current_weight_pct":9.0709666309,
    "previous_weight_pct":9.1240155377,
    "weight_diff_pct":-0.0530489068,
    "change_state":"감소",
    "asof_date":"2026-06-09",
    "source":"FunETF"
  },
  {
    "manager":"삼성",
    "etf_name":"KoAct 바이오헬스케어액티브",
    "short_code":"462900",
    "fund_code":"KR7462900002",
    "holding_name":"셀트리온",
    "current_weight_pct":8.8413541423,
    "previous_weight_pct":8.3258896877,
    "weight_diff_pct":0.5154644545,
    "change_state":"증가",
    "asof_date":"2026-06-09",
    "source":"FunETF"
  },
  {
    "manager":"삼성",
    "etf_name":"KoAct 바이오헬스케어액티브",
    "short_code":"462900",
    "fund_code":"KR7462900002",
    "holding_name":"올릭스",
    "current_weight_pct":8.3884491417,
    "previous_weight_pct":8.930845051,
    "weight_diff_pct":-0.5423959093,
    "change_state":"감소",
    "asof_date":"2026-06-09",
    "source":"FunETF"
  },
  {
    "manager":"DB자산운용",
    "etf_name":"마이티 바이오시밀러&CDMO액티브",
    "short_code":"0001P0",
    "fund_code":"KR70001P0005",
    "holding_name":"셀트리온",
    "current_weight_pct":12.5791563469,
    "previous_weight_pct":12.2614066903,
    "weight_diff_pct":0.3177496566,
    "change_state":"증가",
    "asof_date":"2026-06-09",
    "source":"FunETF"
  },
  {
    "manager":"DB자산운용",
    "etf_name":"마이티 바이오시밀러&CDMO액티브",
    "short_code":"0001P0",
    "fund_code":"KR70001P0005",
    "holding_name":"삼성바이오로직스",
    "current_weight_pct":12.3870653935,
    "previous_weight_pct":12.1051000137,
    "weight_diff_pct":0.2819653799,
    "change_state":"증가",
    "asof_date":"2026-06-09",
    "source":"FunETF"
  },
  {
    "manager":"DB자산운용",
    "etf_name":"마이티 바이오시밀러&CDMO액티브",
    "short_code":"0001P0",
    "fund_code":"KR70001P0005",
    "holding_name":"에스티팜",
    "current_weight_pct":12.2983189421,
    "previous_weight_pct":12.1665044641,
    "weight_diff_pct":0.131814478,
    "change_state":"증가",
    "asof_date":"2026-06-09",
    "source":"FunETF"
  },
  {
    "manager":"KB운용",
    "etf_name":"RISE 바이오TOP10액티브",
    "short_code":"0000Z0",
    "fund_code":"KR70000Z0006",
    "holding_name":"알테오젠",
    "current_weight_pct":12.1190332177,
    "previous_weight_pct":14.153271263,
    "weight_diff_pct":-2.0342380453,
    "change_state":"감소",
    "asof_date":"2026-06-09",
    "source":"FunETF"
  },
  {
    "manager":"KB운용",
    "etf_name":"RISE 바이오TOP10액티브",
    "short_code":"0000Z0",
    "fund_code":"KR70000Z0006",
    "holding_name":"올릭스",
    "current_weight_pct":11.1662395415,
    "previous_weight_pct":13.7571329061,
    "weight_diff_pct":-2.5908933645,
    "change_state":"감소",
    "asof_date":"2026-06-09",
    "source":"FunETF"
  },
  {
    "manager":"KB운용",
    "etf_name":"RISE 바이오TOP10액티브",
    "short_code":"0000Z0",
    "fund_code":"KR70000Z0006",
    "holding_name":"리가켐바이오",
    "current_weight_pct":9.0867079072,
    "previous_weight_pct":10.1729712613,
    "weight_diff_pct":-1.0862633541,
    "change_state":"감소",
    "asof_date":"2026-06-09",
    "source":"FunETF"
  },
  {
    "manager":"현대자산운용",
    "etf_name":"UNICORN K바이오액티브",
    "short_code":"0184V0",
    "fund_code":"KR70184V0007",
    "holding_name":"리가켐바이오",
    "current_weight_pct":8.8371148058,
    "previous_weight_pct":8.9280900554,
    "weight_diff_pct":-0.0909752496,
    "change_state":"감소",
    "asof_date":"2026-06-09",
    "source":"FunETF"
  },
  {
    "manager":"현대자산운용",
    "etf_name":"UNICORN K바이오액티브",
    "short_code":"0184V0",
    "fund_code":"KR70184V0007",
    "holding_name":"에이비엘바이오",
    "current_weight_pct":7.819589803,
    "previous_weight_pct":null,
    "weight_diff_pct":null,
    "change_state":"신규",
    "asof_date":"2026-06-09",
    "source":"FunETF"
  },
  {
    "manager":"현대자산운용",
    "etf_name":"UNICORN K바이오액티브",
    "short_code":"0184V0",
    "fund_code":"KR70184V0007",
    "holding_name":"에이프릴바이오",
    "current_weight_pct":7.5800262475,
    "previous_weight_pct":8.0261345359,
    "weight_diff_pct":-0.4461082884,
    "change_state":"감소",
    "asof_date":"2026-06-09",
    "source":"FunETF"
  }
]