[
  {
    "manager":"삼성",
    "etf_name":"KODEX CD금리액티브(합성)",
    "short_code":"459580",
    "fund_code":"K55105E24776",
    "detail_url":"",
    "source":"FunETF",
    "asset_class":"금리형",
    "style":"액티브",
    "theme":"금리형",
    "category_tags":"금리형 | 액티브 | 단기금리형(파킹형)",
    "aum_okr":81416.40849446,
    "aum_unit":"억원",
    "asof_date":"2026-03-27",
    "fetched_at_utc":"2026-03-27T06:34:10.354187+00:00",
    "error":"",
    "run_date_kst":"2026-03-27T15:34:10.354394+09:00"
  },
  {
    "manager":"삼성",
    "etf_name":"KODEX 머니마켓액티브",
    "short_code":"488770",
    "fund_code":"K55105EC8033",
    "detail_url":"",
    "source":"FunETF",
    "asset_class":"채권",
    "style":"액티브",
    "theme":"금리형",
    "category_tags":"채권 | 액티브 | 금리형 | 단기금리형(파킹형)",
    "aum_okr":78812.72827415,
    "aum_unit":"억원",
    "asof_date":"2026-03-27",
    "fetched_at_utc":"2026-03-27T06:34:10.354187+00:00",
    "error":"",
    "run_date_kst":"2026-03-27T15:34:10.354394+09:00"
  },
  {
    "manager":"삼성",
    "etf_name":"KODEX KOFR금리액티브(합성)",
    "short_code":"423160",
    "fund_code":"K55105DR9373",
    "detail_url":"",
    "source":"FunETF",
    "asset_class":"금리형",
    "style":"액티브",
    "theme":"금리형",
    "category_tags":"금리형 | 액티브 | 단기금리형(파킹형)",
    "aum_okr":44511.95069318,
    "aum_unit":"억원",
    "asof_date":"2026-03-27",
    "fetched_at_utc":"2026-03-27T06:34:10.354187+00:00",
    "error":"",
    "run_date_kst":"2026-03-27T15:34:10.354394+09:00"
  },
  {
    "manager":"삼성",
    "etf_name":"KODEX 종합채권(AA-이상)액티브",
    "short_code":"273130",
    "fund_code":"K55105BR0838",
    "detail_url":"",
    "source":"FunETF",
    "asset_class":"채권",
    "style":"액티브",
    "theme":"채권",
    "category_tags":"채권 | 액티브 | 종합채권",
    "aum_okr":39290.89367841,
    "aum_unit":"억원",
    "asof_date":"2026-03-27",
    "fetched_at_utc":"2026-03-27T06:34:10.354187+00:00",
    "error":"",
    "run_date_kst":"2026-03-27T15:34:10.354394+09:00"
  },
  {
    "manager":"미래에셋",
    "etf_name":"TIGER 머니마켓액티브",
    "short_code":"0043B0",
    "fund_code":"K55301EI2420",
    "detail_url":"",
    "source":"FunETF",
    "asset_class":"채권",
    "style":"액티브",
    "theme":"금리형",
    "category_tags":"채권 | 액티브 | 금리형 | 단기금리형(파킹형)",
    "aum_okr":33195.3482328,
    "aum_unit":"억원",
    "asof_date":"2026-03-27",
    "fetched_at_utc":"2026-03-27T06:34:10.354187+00:00",
    "error":"",
    "run_date_kst":"2026-03-27T15:34:10.354394+09:00"
  },
  {
    "manager":"삼성",
    "etf_name":"KODEX CD1년금리플러스액티브(합성)",
    "short_code":"481050",
    "fund_code":"K55105E94878",
    "detail_url":"",
    "source":"FunETF",
    "asset_class":"금리형",
    "style":"액티브",
    "theme":"금리형",
    "category_tags":"금리형 | 액티브 | 단기금리형(파킹형)",
    "aum_okr":27772.00131969,
    "aum_unit":"억원",
    "asof_date":"2026-03-27",
    "fetched_at_utc":"2026-03-27T06:34:10.354187+00:00",
    "error":"",
    "run_date_kst":"2026-03-27T15:34:10.354394+09:00"
  },
  {
    "manager":"미래에셋",
    "etf_name":"TIGER KOFR금리액티브(합성)",
    "short_code":"449170",
    "fund_code":"K55301DY1209",
    "detail_url":"",
    "source":"FunETF",
    "asset_class":"금리형",
    "style":"액티브",
    "theme":"금리형",
    "category_tags":"금리형 | 액티브 | 단기금리형(파킹형)",
    "aum_okr":24305.8678171,
    "aum_unit":"억원",
    "asof_date":"2026-03-27",
    "fetched_at_utc":"2026-03-27T06:34:10.354187+00:00",
    "error":"",
    "run_date_kst":"2026-03-27T15:34:10.354394+09:00"
  },
  {
    "manager":"미래에셋",
    "etf_name":"TIGER CD1년금리액티브(합성)",
    "short_code":"475630",
    "fund_code":"K55301E85343",
    "detail_url":"",
    "source":"FunETF",
    "asset_class":"금리형",
    "style":"액티브",
    "theme":"금리형",
    "category_tags":"금리형 | 액티브 | 단기금리형(파킹형)",
    "aum_okr":15988.33285215,
    "aum_unit":"억원",
    "asof_date":"2026-03-27",
    "fetched_at_utc":"2026-03-27T06:34:10.354187+00:00",
    "error":"",
    "run_date_kst":"2026-03-27T15:34:10.354394+09:00"
  },
  {
    "manager":"삼성",
    "etf_name":"KODEX 26-12 금융채(AA-이상)액티브",
    "short_code":"0117L0",
    "fund_code":"K55105EN8634",
    "detail_url":"",
    "source":"FunETF",
    "asset_class":"채권",
    "style":"액티브",
    "theme":"채권",
    "category_tags":"채권 | 액티브",
    "aum_okr":14487.07708577,
    "aum_unit":"억원",
    "asof_date":"2026-03-27",
    "fetched_at_utc":"2026-03-27T06:34:10.354187+00:00",
    "error":"",
    "run_date_kst":"2026-03-27T15:34:10.354394+09:00"
  },
  {
    "manager":"미래에셋",
    "etf_name":"TIGER 12월자동연장금융채(AA-이상)액티브",
    "short_code":"0139F0",
    "fund_code":"K55301EP6638",
    "detail_url":"",
    "source":"FunETF",
    "asset_class":"채권",
    "style":"액티브",
    "theme":"채권",
    "category_tags":"채권 | 액티브",
    "aum_okr":11875.50904259,
    "aum_unit":"억원",
    "asof_date":"2026-03-27",
    "fetched_at_utc":"2026-03-27T06:34:10.354187+00:00",
    "error":"",
    "run_date_kst":"2026-03-27T15:34:10.354394+09:00"
  },
  {
    "manager":"미래에셋",
    "etf_name":"TIGER 종합채권(AA-이상)액티브",
    "short_code":"451540",
    "fund_code":"K55301DZ7460",
    "detail_url":"",
    "source":"FunETF",
    "asset_class":"채권",
    "style":"액티브",
    "theme":"채권",
    "category_tags":"채권 | 액티브 | 종합채권",
    "aum_okr":10686.2777243,
    "aum_unit":"억원",
    "asof_date":"2026-03-27",
    "fetched_at_utc":"2026-03-27T06:34:10.354187+00:00",
    "error":"",
    "run_date_kst":"2026-03-27T15:34:10.354394+09:00"
  },
  {
    "manager":"삼성",
    "etf_name":"KoAct 코스닥액티브",
    "short_code":"0163Y0",
    "fund_code":"K553N9EU4486",
    "detail_url":"",
    "source":"FunETF",
    "asset_class":"주식",
    "style":"액티브",
    "theme":"기타",
    "category_tags":"주식 | 액티브",
    "aum_okr":10190.28674232,
    "aum_unit":"억원",
    "asof_date":"2026-03-27",
    "fetched_at_utc":"2026-03-27T06:34:10.354187+00:00",
    "error":"",
    "run_date_kst":"2026-03-27T15:34:10.354394+09:00"
  },
  {
    "manager":"삼성",
    "etf_name":"KODEX 로봇액티브",
    "short_code":"445290",
    "fund_code":"K55105DW7453",
    "detail_url":"",
    "source":"FunETF",
    "asset_class":"주식",
    "style":"액티브",
    "theme":"AI",
    "category_tags":"주식 | 액티브 | AI |  AI&로봇",
    "aum_okr":9795.13608357,
    "aum_unit":"억원",
    "asof_date":"2026-03-27",
    "fetched_at_utc":"2026-03-27T06:34:10.354187+00:00",
    "error":"",
    "run_date_kst":"2026-03-27T15:34:10.354394+09:00"
  },
  {
    "manager":"삼성",
    "etf_name":"KODEX 200액티브",
    "short_code":"494890",
    "fund_code":"K55105EE6431",
    "detail_url":"",
    "source":"FunETF",
    "asset_class":"주식",
    "style":"액티브",
    "theme":"기타",
    "category_tags":"주식 | 액티브 | 코스피 200",
    "aum_okr":9356.81208312,
    "aum_unit":"억원",
    "asof_date":"2026-03-27",
    "fetched_at_utc":"2026-03-27T06:34:10.354187+00:00",
    "error":"",
    "run_date_kst":"2026-03-27T15:34:10.354394+09:00"
  },
  {
    "manager":"미래에셋",
    "etf_name":"TIGER 배당커버드콜액티브",
    "short_code":"472150",
    "fund_code":"K55301DY9046",
    "detail_url":"",
    "source":"FunETF",
    "asset_class":"주식",
    "style":"커버드콜",
    "theme":"배당",
    "category_tags":"주식 | 커버드콜 | 배당",
    "aum_okr":8724.69174401,
    "aum_unit":"억원",
    "asof_date":"2026-03-27",
    "fetched_at_utc":"2026-03-27T06:34:10.354187+00:00",
    "error":"",
    "run_date_kst":"2026-03-27T15:34:10.354394+09:00"
  },
  {
    "manager":"미래에셋",
    "etf_name":"TIGER 단기채권액티브",
    "short_code":"272580",
    "fund_code":"K55301BR4790",
    "detail_url":"",
    "source":"FunETF",
    "asset_class":"채권",
    "style":"액티브",
    "theme":"채권",
    "category_tags":"채권 | 액티브",
    "aum_okr":7624.40512333,
    "aum_unit":"억원",
    "asof_date":"2026-03-27",
    "fetched_at_utc":"2026-03-27T06:34:10.354187+00:00",
    "error":"",
    "run_date_kst":"2026-03-27T15:34:10.354394+09:00"
  },
  {
    "manager":"미래에셋",
    "etf_name":"TIGER 우량회사채액티브",
    "short_code":"438330",
    "fund_code":"K55301DW0609",
    "detail_url":"",
    "source":"FunETF",
    "asset_class":"채권",
    "style":"액티브",
    "theme":"채권",
    "category_tags":"채권 | 액티브",
    "aum_okr":6813.42996944,
    "aum_unit":"억원",
    "asof_date":"2026-03-27",
    "fetched_at_utc":"2026-03-27T06:34:10.354187+00:00",
    "error":"",
    "run_date_kst":"2026-03-27T15:34:10.354394+09:00"
  },
  {
    "manager":"타임폴리오",
    "etf_name":"TIME Korea플러스배당액티브",
    "short_code":"441800",
    "fund_code":"K553J1DW4846",
    "detail_url":"",
    "source":"FunETF",
    "asset_class":"주식",
    "style":"액티브",
    "theme":"배당",
    "category_tags":"주식 | 액티브 | 배당 | 국내",
    "aum_okr":6777.30738824,
    "aum_unit":"억원",
    "asof_date":"2026-03-27",
    "fetched_at_utc":"2026-03-27T06:34:10.354187+00:00",
    "error":"",
    "run_date_kst":"2026-03-27T15:34:10.354394+09:00"
  },
  {
    "manager":"삼성",
    "etf_name":"KoAct 바이오헬스케어액티브",
    "short_code":"462900",
    "fund_code":"K553N9E27494",
    "detail_url":"",
    "source":"FunETF",
    "asset_class":"주식",
    "style":"액티브",
    "theme":"바이오",
    "category_tags":"주식 | 액티브 | 바이오 | 바이오헬스",
    "aum_okr":6424.54184968,
    "aum_unit":"억원",
    "asof_date":"2026-03-27",
    "fetched_at_utc":"2026-03-27T06:34:10.354187+00:00",
    "error":"",
    "run_date_kst":"2026-03-27T15:34:10.354394+09:00"
  },
  {
    "manager":"타임폴리오",
    "etf_name":"TIME 코스닥액티브",
    "short_code":"0162Y0",
    "fund_code":"K553J1ET1739",
    "detail_url":"",
    "source":"FunETF",
    "asset_class":"주식",
    "style":"액티브",
    "theme":"기타",
    "category_tags":"주식 | 액티브",
    "aum_okr":5466.83464641,
    "aum_unit":"억원",
    "asof_date":"2026-03-27",
    "fetched_at_utc":"2026-03-27T06:34:10.354187+00:00",
    "error":"",
    "run_date_kst":"2026-03-27T15:34:10.354394+09:00"
  },
  {
    "manager":"삼성",
    "etf_name":"KODEX 국고채10년액티브",
    "short_code":"471230",
    "fund_code":"K55105E67924",
    "detail_url":"",
    "source":"FunETF",
    "asset_class":"채권",
    "style":"액티브",
    "theme":"채권",
    "category_tags":"채권 | 액티브",
    "aum_okr":5412.72176956,
    "aum_unit":"억원",
    "asof_date":"2026-03-27",
    "fetched_at_utc":"2026-03-27T06:34:10.354187+00:00",
    "error":"",
    "run_date_kst":"2026-03-27T15:34:10.354394+09:00"
  },
  {
    "manager":"삼성",
    "etf_name":"KODEX 26-12 회사채(AA-이상)액티브",
    "short_code":"473290",
    "fund_code":"K55105E71496",
    "detail_url":"",
    "source":"FunETF",
    "asset_class":"채권",
    "style":"액티브",
    "theme":"채권",
    "category_tags":"채권 | 액티브 | AA+미만",
    "aum_okr":5134.36642135,
    "aum_unit":"억원",
    "asof_date":"2026-03-27",
    "fetched_at_utc":"2026-03-27T06:34:10.354187+00:00",
    "error":"",
    "run_date_kst":"2026-03-27T15:34:10.354394+09:00"
  },
  {
    "manager":"삼성",
    "etf_name":"KODEX TDF2050액티브",
    "short_code":"434060",
    "fund_code":"K55105DT5379",
    "detail_url":"",
    "source":"FunETF",
    "asset_class":"채권",
    "style":"액티브",
    "theme":"기타",
    "category_tags":"채권 | 액티브",
    "aum_okr":4901.16743195,
    "aum_unit":"억원",
    "asof_date":"2026-03-27",
    "fetched_at_utc":"2026-03-27T06:34:10.354187+00:00",
    "error":"",
    "run_date_kst":"2026-03-27T15:34:10.354394+09:00"
  },
  {
    "manager":"미래에셋",
    "etf_name":"TIGER 27-04회사채(A+이상)액티브",
    "short_code":"480260",
    "fund_code":"K55301E99955",
    "detail_url":"",
    "source":"FunETF",
    "asset_class":"채권",
    "style":"액티브",
    "theme":"채권",
    "category_tags":"채권 | 액티브 | AA+미만",
    "aum_okr":4805.60189443,
    "aum_unit":"억원",
    "asof_date":"2026-03-27",
    "fetched_at_utc":"2026-03-27T06:34:10.354187+00:00",
    "error":"",
    "run_date_kst":"2026-03-27T15:34:10.354394+09:00"
  },
  {
    "manager":"타임폴리오",
    "etf_name":"TIME K바이오액티브",
    "short_code":"463050",
    "fund_code":"K553J1E46927",
    "detail_url":"",
    "source":"FunETF",
    "asset_class":"주식",
    "style":"액티브",
    "theme":"바이오",
    "category_tags":"주식 | 액티브 | 바이오 | 바이오헬스",
    "aum_okr":4663.35456894,
    "aum_unit":"억원",
    "asof_date":"2026-03-27",
    "fetched_at_utc":"2026-03-27T06:34:10.354187+00:00",
    "error":"",
    "run_date_kst":"2026-03-27T15:34:10.354394+09:00"
  },
  {
    "manager":"미래에셋",
    "etf_name":"TIGER CD금리플러스액티브(합성)",
    "short_code":"499660",
    "fund_code":"K55301EF8008",
    "detail_url":"",
    "source":"FunETF",
    "asset_class":"금리형",
    "style":"액티브",
    "theme":"금리형",
    "category_tags":"금리형 | 액티브 | 단기금리형(파킹형)",
    "aum_okr":4338.48060703,
    "aum_unit":"억원",
    "asof_date":"2026-03-27",
    "fetched_at_utc":"2026-03-27T06:34:10.354187+00:00",
    "error":"",
    "run_date_kst":"2026-03-27T15:34:10.354394+09:00"
  },
  {
    "manager":"삼성",
    "etf_name":"KODEX 27-12 회사채(AA-이상)액티브",
    "short_code":"0007F0",
    "fund_code":"K55105EG9086",
    "detail_url":"",
    "source":"FunETF",
    "asset_class":"채권",
    "style":"액티브",
    "theme":"채권",
    "category_tags":"채권 | 액티브 | AA+미만",
    "aum_okr":4041.5662902,
    "aum_unit":"억원",
    "asof_date":"2026-03-27",
    "fetched_at_utc":"2026-03-27T06:34:10.354187+00:00",
    "error":"",
    "run_date_kst":"2026-03-27T15:34:10.354394+09:00"
  },
  {
    "manager":"삼성",
    "etf_name":"KODEX 국고채30년액티브",
    "short_code":"439870",
    "fund_code":"K55105DV4568",
    "detail_url":"",
    "source":"FunETF",
    "asset_class":"채권",
    "style":"액티브",
    "theme":"채권",
    "category_tags":"채권 | 액티브 | 국내",
    "aum_okr":3534.56064,
    "aum_unit":"억원",
    "asof_date":"2026-03-27",
    "fetched_at_utc":"2026-03-27T06:34:10.354187+00:00",
    "error":"",
    "run_date_kst":"2026-03-27T15:34:10.354394+09:00"
  },
  {
    "manager":"삼성",
    "etf_name":"KODEX 테슬라커버드콜채권혼합액티브",
    "short_code":"475080",
    "fund_code":"K55105E76727",
    "detail_url":"",
    "source":"FunETF",
    "asset_class":"채권",
    "style":"커버드콜",
    "theme":"커버드콜",
    "category_tags":"채권 | 커버드콜",
    "aum_okr":3432.19376497,
    "aum_unit":"억원",
    "asof_date":"2026-03-27",
    "fetched_at_utc":"2026-03-27T06:34:10.354187+00:00",
    "error":"",
    "run_date_kst":"2026-03-27T15:34:10.354394+09:00"
  },
  {
    "manager":"삼성",
    "etf_name":"KODEX 단기변동금리부채권액티브",
    "short_code":"273140",
    "fund_code":"K55105BR3113",
    "detail_url":"",
    "source":"FunETF",
    "asset_class":"채권",
    "style":"액티브",
    "theme":"금리형",
    "category_tags":"채권 | 액티브 | 금리형",
    "aum_okr":3269.65487523,
    "aum_unit":"억원",
    "asof_date":"2026-03-27",
    "fetched_at_utc":"2026-03-27T06:34:10.354187+00:00",
    "error":"",
    "run_date_kst":"2026-03-27T15:34:10.354394+09:00"
  },
  {
    "manager":"삼성",
    "etf_name":"KODEX ESG종합채권(A-이상)액티브",
    "short_code":"439860",
    "fund_code":"K55105DR2899",
    "detail_url":"",
    "source":"FunETF",
    "asset_class":"채권",
    "style":"액티브",
    "theme":"채권",
    "category_tags":"채권 | 액티브 | 종합채권",
    "aum_okr":3149.26799386,
    "aum_unit":"억원",
    "asof_date":"2026-03-27",
    "fetched_at_utc":"2026-03-27T06:34:10.354187+00:00",
    "error":"",
    "run_date_kst":"2026-03-27T15:34:10.354394+09:00"
  },
  {
    "manager":"삼성",
    "etf_name":"KODEX 장기종합채권(AA-이상)액티브",
    "short_code":"363570",
    "fund_code":"K55105D79160",
    "detail_url":"",
    "source":"FunETF",
    "asset_class":"채권",
    "style":"액티브",
    "theme":"채권",
    "category_tags":"채권 | 액티브 | 종합채권",
    "aum_okr":3132.69779635,
    "aum_unit":"억원",
    "asof_date":"2026-03-27",
    "fetched_at_utc":"2026-03-27T06:34:10.354187+00:00",
    "error":"",
    "run_date_kst":"2026-03-27T15:34:10.354394+09:00"
  },
  {
    "manager":"미래에셋",
    "etf_name":"TIGER 28-04 회사채(A+이상)액티브",
    "short_code":"0094K0",
    "fund_code":"K55301EM5013",
    "detail_url":"",
    "source":"FunETF",
    "asset_class":"채권",
    "style":"액티브",
    "theme":"채권",
    "category_tags":"채권 | 액티브 | AA+미만",
    "aum_okr":2937.08722096,
    "aum_unit":"억원",
    "asof_date":"2026-03-27",
    "fetched_at_utc":"2026-03-27T06:34:10.354187+00:00",
    "error":"",
    "run_date_kst":"2026-03-27T15:34:10.354394+09:00"
  },
  {
    "manager":"삼성",
    "etf_name":"KODEX 신재생에너지액티브",
    "short_code":"385510",
    "fund_code":"K55105DH2776",
    "detail_url":"",
    "source":"FunETF",
    "asset_class":"주식",
    "style":"액티브",
    "theme":"전력\/에너지",
    "category_tags":"주식 | 액티브 | 전력\/에너지 | 에너지&화학",
    "aum_okr":2907.99739906,
    "aum_unit":"억원",
    "asof_date":"2026-03-27",
    "fetched_at_utc":"2026-03-27T06:34:10.354187+00:00",
    "error":"",
    "run_date_kst":"2026-03-27T15:34:10.354394+09:00"
  },
  {
    "manager":"타임폴리오",
    "etf_name":"TIME 코스피액티브",
    "short_code":"385720",
    "fund_code":"K553J1DJ0270",
    "detail_url":"",
    "source":"FunETF",
    "asset_class":"주식",
    "style":"액티브",
    "theme":"기타",
    "category_tags":"주식 | 액티브",
    "aum_okr":2651.57488802,
    "aum_unit":"억원",
    "asof_date":"2026-03-27",
    "fetched_at_utc":"2026-03-27T06:34:10.354187+00:00",
    "error":"",
    "run_date_kst":"2026-03-27T15:34:10.354394+09:00"
  },
  {
    "manager":"삼성",
    "etf_name":"KoAct 코리아밸류업액티브",
    "short_code":"495230",
    "fund_code":"K553N9EF9468",
    "detail_url":"",
    "source":"FunETF",
    "asset_class":"주식",
    "style":"액티브",
    "theme":"기타",
    "category_tags":"주식 | 액티브",
    "aum_okr":2344.00716363,
    "aum_unit":"억원",
    "asof_date":"2026-03-27",
    "fetched_at_utc":"2026-03-27T06:34:10.354187+00:00",
    "error":"",
    "run_date_kst":"2026-03-27T15:34:10.354394+09:00"
  },
  {
    "manager":"미래에셋",
    "etf_name":"TIGER 26-04 회사채(A+이상)액티브",
    "short_code":"0001S0",
    "fund_code":"K55301EG5110",
    "detail_url":"",
    "source":"FunETF",
    "asset_class":"채권",
    "style":"액티브",
    "theme":"채권",
    "category_tags":"채권 | 액티브 | AA+미만",
    "aum_okr":1774.239532,
    "aum_unit":"억원",
    "asof_date":"2026-03-27",
    "fetched_at_utc":"2026-03-27T06:34:10.354187+00:00",
    "error":"",
    "run_date_kst":"2026-03-27T15:34:10.354394+09:00"
  },
  {
    "manager":"삼성",
    "etf_name":"KODEX 28-12 회사채(AA-이상)액티브",
    "short_code":"0119H0",
    "fund_code":"K55105EN8642",
    "detail_url":"",
    "source":"FunETF",
    "asset_class":"채권",
    "style":"액티브",
    "theme":"채권",
    "category_tags":"채권 | 액티브",
    "aum_okr":1634.7034268,
    "aum_unit":"억원",
    "asof_date":"2026-03-27",
    "fetched_at_utc":"2026-03-27T06:34:10.354187+00:00",
    "error":"",
    "run_date_kst":"2026-03-27T15:34:10.354394+09:00"
  },
  {
    "manager":"타임폴리오",
    "etf_name":"TIME 코리아밸류업액티브",
    "short_code":"495060",
    "fund_code":"K553J1EF9274",
    "detail_url":"",
    "source":"FunETF",
    "asset_class":"주식",
    "style":"액티브",
    "theme":"기타",
    "category_tags":"주식 | 액티브",
    "aum_okr":1468.44853194,
    "aum_unit":"억원",
    "asof_date":"2026-03-27",
    "fetched_at_utc":"2026-03-27T06:34:10.354187+00:00",
    "error":"",
    "run_date_kst":"2026-03-27T15:34:10.354394+09:00"
  },
  {
    "manager":"미래에셋",
    "etf_name":"TIGER 국고채30년스트립액티브",
    "short_code":"451530",
    "fund_code":"K55301DZ7882",
    "detail_url":"",
    "source":"FunETF",
    "asset_class":"채권",
    "style":"액티브",
    "theme":"채권",
    "category_tags":"채권 | 액티브 | 국내",
    "aum_okr":1416.93056961,
    "aum_unit":"억원",
    "asof_date":"2026-03-27",
    "fetched_at_utc":"2026-03-27T06:34:10.354187+00:00",
    "error":"",
    "run_date_kst":"2026-03-27T15:34:10.354394+09:00"
  },
  {
    "manager":"삼성",
    "etf_name":"KODEX 금융채1~2년(AA-이상)PLUS액티브",
    "short_code":"0162M0",
    "fund_code":"K55105ER7764",
    "detail_url":"",
    "source":"FunETF",
    "asset_class":"채권",
    "style":"액티브",
    "theme":"채권",
    "category_tags":"채권 | 액티브",
    "aum_okr":1372.85541884,
    "aum_unit":"억원",
    "asof_date":"2026-03-27",
    "fetched_at_utc":"2026-03-27T06:34:10.354187+00:00",
    "error":"",
    "run_date_kst":"2026-03-27T15:34:10.354394+09:00"
  },
  {
    "manager":"삼성",
    "etf_name":"KoAct K수출핵심기업TOP30액티브",
    "short_code":"0074K0",
    "fund_code":"K553N9EL0774",
    "detail_url":"",
    "source":"FunETF",
    "asset_class":"주식",
    "style":"액티브",
    "theme":"기타",
    "category_tags":"주식 | 액티브",
    "aum_okr":1288.7290685,
    "aum_unit":"억원",
    "asof_date":"2026-03-27",
    "fetched_at_utc":"2026-03-27T06:34:10.354187+00:00",
    "error":"",
    "run_date_kst":"2026-03-27T15:34:10.354394+09:00"
  },
  {
    "manager":"삼성",
    "etf_name":"KODEX TDF2040액티브",
    "short_code":"433980",
    "fund_code":"K55105DT5361",
    "detail_url":"",
    "source":"FunETF",
    "asset_class":"채권",
    "style":"액티브",
    "theme":"기타",
    "category_tags":"채권 | 액티브",
    "aum_okr":1244.66460056,
    "aum_unit":"억원",
    "asof_date":"2026-03-27",
    "fetched_at_utc":"2026-03-27T06:34:10.354187+00:00",
    "error":"",
    "run_date_kst":"2026-03-27T15:34:10.354394+09:00"
  },
  {
    "manager":"삼성",
    "etf_name":"KODEX TDF2060액티브",
    "short_code":"0082V0",
    "fund_code":"K55105EI4473",
    "detail_url":"",
    "source":"FunETF",
    "asset_class":"채권",
    "style":"액티브",
    "theme":"기타",
    "category_tags":"채권 | 액티브",
    "aum_okr":1151.9319496,
    "aum_unit":"억원",
    "asof_date":"2026-03-27",
    "fetched_at_utc":"2026-03-27T06:34:10.354187+00:00",
    "error":"",
    "run_date_kst":"2026-03-27T15:34:10.354394+09:00"
  },
  {
    "manager":"미래에셋",
    "etf_name":"TIGER 기술이전바이오액티브",
    "short_code":"0168K0",
    "fund_code":"K55301EQ3782",
    "detail_url":"",
    "source":"FunETF",
    "asset_class":"주식",
    "style":"액티브",
    "theme":"바이오",
    "category_tags":"주식 | 액티브 | 바이오",
    "aum_okr":1089.47231734,
    "aum_unit":"억원",
    "asof_date":"2026-03-27",
    "fetched_at_utc":"2026-03-27T06:34:10.354187+00:00",
    "error":"",
    "run_date_kst":"2026-03-27T15:34:10.354394+09:00"
  },
  {
    "manager":"미래에셋",
    "etf_name":"TIGER 리츠부동산인프라TOP10액티브",
    "short_code":"0086B0",
    "fund_code":"K55301EL4868",
    "detail_url":"",
    "source":"FunETF",
    "asset_class":"부동산\/리츠",
    "style":"액티브",
    "theme":"리츠\/부동산",
    "category_tags":"부동산\/리츠 | 액티브 | 리츠\/부동산",
    "aum_okr":927.87156319,
    "aum_unit":"억원",
    "asof_date":"2026-03-27",
    "fetched_at_utc":"2026-03-27T06:34:10.354187+00:00",
    "error":"",
    "run_date_kst":"2026-03-27T15:34:10.354394+09:00"
  },
  {
    "manager":"삼성",
    "etf_name":"KODEX TDF2030액티브",
    "short_code":"433970",
    "fund_code":"K55105DT5353",
    "detail_url":"",
    "source":"FunETF",
    "asset_class":"채권",
    "style":"액티브",
    "theme":"기타",
    "category_tags":"채권 | 액티브",
    "aum_okr":810.72624564,
    "aum_unit":"억원",
    "asof_date":"2026-03-27",
    "fetched_at_utc":"2026-03-27T06:34:10.354187+00:00",
    "error":"",
    "run_date_kst":"2026-03-27T15:34:10.354394+09:00"
  },
  {
    "manager":"삼성",
    "etf_name":"KoAct 배당성장액티브",
    "short_code":"476850",
    "fund_code":"K553N9E80501",
    "detail_url":"",
    "source":"FunETF",
    "asset_class":"주식",
    "style":"액티브",
    "theme":"배당",
    "category_tags":"주식 | 액티브 | 배당",
    "aum_okr":795.40647685,
    "aum_unit":"억원",
    "asof_date":"2026-03-27",
    "fetched_at_utc":"2026-03-27T06:34:10.354187+00:00",
    "error":"",
    "run_date_kst":"2026-03-27T15:34:10.354394+09:00"
  },
  {
    "manager":"삼성",
    "etf_name":"KODEX 메타버스액티브",
    "short_code":"401470",
    "fund_code":"K55105DM5970",
    "detail_url":"",
    "source":"FunETF",
    "asset_class":"주식",
    "style":"액티브",
    "theme":"기타",
    "category_tags":"주식 | 액티브",
    "aum_okr":752.35321613,
    "aum_unit":"억원",
    "asof_date":"2026-03-27",
    "fetched_at_utc":"2026-03-27T06:34:10.354187+00:00",
    "error":"",
    "run_date_kst":"2026-03-27T15:34:10.354394+09:00"
  },
  {
    "manager":"미래에셋",
    "etf_name":"TIGER 코리아테크액티브",
    "short_code":"471780",
    "fund_code":"K55301E68232",
    "detail_url":"",
    "source":"FunETF",
    "asset_class":"주식",
    "style":"액티브",
    "theme":"기타",
    "category_tags":"주식 | 액티브",
    "aum_okr":674.65628876,
    "aum_unit":"억원",
    "asof_date":"2026-03-27",
    "fetched_at_utc":"2026-03-27T06:34:10.354187+00:00",
    "error":"",
    "run_date_kst":"2026-03-27T15:34:10.354394+09:00"
  },
  {
    "manager":"삼성",
    "etf_name":"KODEX 친환경조선해운액티브",
    "short_code":"445150",
    "fund_code":"K55105DW7461",
    "detail_url":"",
    "source":"FunETF",
    "asset_class":"주식",
    "style":"액티브",
    "theme":"전력\/에너지",
    "category_tags":"주식 | 액티브 | 전력\/에너지 | 조선",
    "aum_okr":674.61008218,
    "aum_unit":"억원",
    "asof_date":"2026-03-27",
    "fetched_at_utc":"2026-03-27T06:34:10.354187+00:00",
    "error":"",
    "run_date_kst":"2026-03-27T15:34:10.354394+09:00"
  },
  {
    "manager":"미래에셋",
    "etf_name":"TIGER AI코리아그로스액티브",
    "short_code":"365040",
    "fund_code":"K55301D98900",
    "detail_url":"",
    "source":"FunETF",
    "asset_class":"주식",
    "style":"액티브",
    "theme":"AI",
    "category_tags":"주식 | 액티브 | AI |  AI&로봇",
    "aum_okr":553.78391295,
    "aum_unit":"억원",
    "asof_date":"2026-03-27",
    "fetched_at_utc":"2026-03-27T06:34:10.354187+00:00",
    "error":"",
    "run_date_kst":"2026-03-27T15:34:10.354394+09:00"
  },
  {
    "manager":"타임폴리오",
    "etf_name":"TIME K컬처액티브",
    "short_code":"410870",
    "fund_code":"K553J1DP1767",
    "detail_url":"",
    "source":"FunETF",
    "asset_class":"주식",
    "style":"액티브",
    "theme":"기타",
    "category_tags":"주식 | 액티브",
    "aum_okr":421.34874502,
    "aum_unit":"억원",
    "asof_date":"2026-03-27",
    "fetched_at_utc":"2026-03-27T06:34:10.354187+00:00",
    "error":"",
    "run_date_kst":"2026-03-27T15:34:10.354394+09:00"
  },
  {
    "manager":"삼성",
    "etf_name":"KoAct 수소전력ESS인프라액티브",
    "short_code":"0150K0",
    "fund_code":"K553N9EQ9994",
    "detail_url":"",
    "source":"FunETF",
    "asset_class":"부동산\/리츠",
    "style":"액티브",
    "theme":"리츠\/부동산",
    "category_tags":"부동산\/리츠 | 액티브 | 리츠\/부동산",
    "aum_okr":419.34139703,
    "aum_unit":"억원",
    "asof_date":"2026-03-27",
    "fetched_at_utc":"2026-03-27T06:34:10.354187+00:00",
    "error":"",
    "run_date_kst":"2026-03-27T15:34:10.354394+09:00"
  },
  {
    "manager":"삼성",
    "etf_name":"KoAct AI인프라액티브",
    "short_code":"487130",
    "fund_code":"K553N9EC3266",
    "detail_url":"",
    "source":"FunETF",
    "asset_class":"부동산\/리츠",
    "style":"액티브",
    "theme":"AI",
    "category_tags":"부동산\/리츠 | 액티브 | AI |  AI&로봇",
    "aum_okr":330.14548374,
    "aum_unit":"억원",
    "asof_date":"2026-03-27",
    "fetched_at_utc":"2026-03-27T06:34:10.354187+00:00",
    "error":"",
    "run_date_kst":"2026-03-27T15:34:10.354394+09:00"
  },
  {
    "manager":"삼성",
    "etf_name":"KODEX 자율주행액티브",
    "short_code":"385520",
    "fund_code":"K55105DH2784",
    "detail_url":"",
    "source":"FunETF",
    "asset_class":"주식",
    "style":"액티브",
    "theme":"모빌리티",
    "category_tags":"주식 | 액티브 | 모빌리티",
    "aum_okr":310.56713169,
    "aum_unit":"억원",
    "asof_date":"2026-03-27",
    "fetched_at_utc":"2026-03-27T06:34:10.354187+00:00",
    "error":"",
    "run_date_kst":"2026-03-27T15:34:10.354394+09:00"
  },
  {
    "manager":"삼성",
    "etf_name":"KODEX 33-06 국고채액티브",
    "short_code":"457690",
    "fund_code":"K55105E17036",
    "detail_url":"",
    "source":"FunETF",
    "asset_class":"채권",
    "style":"액티브",
    "theme":"채권",
    "category_tags":"채권 | 액티브 | AA+이상",
    "aum_okr":212.15929188,
    "aum_unit":"억원",
    "asof_date":"2026-03-27",
    "fetched_at_utc":"2026-03-27T06:34:10.354187+00:00",
    "error":"",
    "run_date_kst":"2026-03-27T15:34:10.354394+09:00"
  },
  {
    "manager":"미래에셋",
    "etf_name":"TIGER 퓨처모빌리티액티브",
    "short_code":"387280",
    "fund_code":"K55301DH5144",
    "detail_url":"",
    "source":"FunETF",
    "asset_class":"주식",
    "style":"액티브",
    "theme":"모빌리티",
    "category_tags":"주식 | 액티브 | 모빌리티",
    "aum_okr":184.40959129,
    "aum_unit":"억원",
    "asof_date":"2026-03-27",
    "fetched_at_utc":"2026-03-27T06:34:10.354187+00:00",
    "error":"",
    "run_date_kst":"2026-03-27T15:34:10.354394+09:00"
  },
  {
    "manager":"삼성",
    "etf_name":"KODEX 혁신기술테마액티브",
    "short_code":"364690",
    "fund_code":"K55105D92619",
    "detail_url":"",
    "source":"FunETF",
    "asset_class":"주식",
    "style":"액티브",
    "theme":"기타",
    "category_tags":"주식 | 액티브",
    "aum_okr":182.21443702,
    "aum_unit":"억원",
    "asof_date":"2026-03-27",
    "fetched_at_utc":"2026-03-27T06:34:10.354187+00:00",
    "error":"",
    "run_date_kst":"2026-03-27T15:34:10.354394+09:00"
  },
  {
    "manager":"미래에셋",
    "etf_name":"TIGER 리츠부동산인프라10채권혼합액티브",
    "short_code":"0086C0",
    "fund_code":"K55301EL7275",
    "detail_url":"",
    "source":"FunETF",
    "asset_class":"채권",
    "style":"액티브",
    "theme":"채권",
    "category_tags":"채권 | 액티브",
    "aum_okr":161.541818,
    "aum_unit":"억원",
    "asof_date":"2026-03-27",
    "fetched_at_utc":"2026-03-27T06:34:10.354187+00:00",
    "error":"",
    "run_date_kst":"2026-03-27T15:34:10.354394+09:00"
  },
  {
    "manager":"삼성",
    "etf_name":"KoAct 반도체&2차전지핵심소재액티브",
    "short_code":"482030",
    "fund_code":"K553N9E96812",
    "detail_url":"",
    "source":"FunETF",
    "asset_class":"주식",
    "style":"액티브",
    "theme":"반도체",
    "category_tags":"주식 | 액티브 | 반도체",
    "aum_okr":151.09612098,
    "aum_unit":"억원",
    "asof_date":"2026-03-27",
    "fetched_at_utc":"2026-03-27T06:34:10.354187+00:00",
    "error":"",
    "run_date_kst":"2026-03-27T15:34:10.354394+09:00"
  },
  {
    "manager":"타임폴리오",
    "etf_name":"TIME K신재생에너지액티브",
    "short_code":"404120",
    "fund_code":"K553J1DO1974",
    "detail_url":"",
    "source":"FunETF",
    "asset_class":"주식",
    "style":"액티브",
    "theme":"전력\/에너지",
    "category_tags":"주식 | 액티브 | 전력\/에너지",
    "aum_okr":138.44215433,
    "aum_unit":"억원",
    "asof_date":"2026-03-27",
    "fetched_at_utc":"2026-03-27T06:34:10.354187+00:00",
    "error":"",
    "run_date_kst":"2026-03-27T15:34:10.354394+09:00"
  },
  {
    "manager":"삼성",
    "etf_name":"KODEX 53-09 국고채액티브",
    "short_code":"457700",
    "fund_code":"K55105E17044",
    "detail_url":"",
    "source":"FunETF",
    "asset_class":"채권",
    "style":"액티브",
    "theme":"채권",
    "category_tags":"채권 | 액티브 | AA+이상",
    "aum_okr":134.79038992,
    "aum_unit":"억원",
    "asof_date":"2026-03-27",
    "fetched_at_utc":"2026-03-27T06:34:10.354187+00:00",
    "error":"",
    "run_date_kst":"2026-03-27T15:34:10.354394+09:00"
  },
  {
    "manager":"타임폴리오",
    "etf_name":"TIME K이노베이션액티브",
    "short_code":"385710",
    "fund_code":"K553J1DJ0288",
    "detail_url":"",
    "source":"FunETF",
    "asset_class":"주식",
    "style":"액티브",
    "theme":"기타",
    "category_tags":"주식 | 액티브",
    "aum_okr":124.69043597,
    "aum_unit":"억원",
    "asof_date":"2026-03-27",
    "fetched_at_utc":"2026-03-27T06:34:10.354187+00:00",
    "error":"",
    "run_date_kst":"2026-03-27T15:34:10.354394+09:00"
  },
  {
    "manager":"삼성",
    "etf_name":"KODEX 코리아혁신성장액티브",
    "short_code":"373490",
    "fund_code":"K55105DC4892",
    "detail_url":"",
    "source":"FunETF",
    "asset_class":"주식",
    "style":"액티브",
    "theme":"기타",
    "category_tags":"주식 | 액티브",
    "aum_okr":120.64175483,
    "aum_unit":"억원",
    "asof_date":"2026-03-27",
    "fetched_at_utc":"2026-03-27T06:34:10.354187+00:00",
    "error":"",
    "run_date_kst":"2026-03-27T15:34:10.354394+09:00"
  },
  {
    "manager":"미래에셋",
    "etf_name":"BNK 미래전략기술액티브",
    "short_code":"457930",
    "fund_code":"K55240E32568",
    "detail_url":"",
    "source":"FunETF",
    "asset_class":"주식",
    "style":"액티브",
    "theme":"기타",
    "category_tags":"주식 | 액티브",
    "aum_okr":80.00031481,
    "aum_unit":"억원",
    "asof_date":"2026-03-27",
    "fetched_at_utc":"2026-03-27T06:34:10.354187+00:00",
    "error":"",
    "run_date_kst":"2026-03-27T15:34:10.354394+09:00"
  }
]